{
  "QC1LPE435": "Q10E",
  "QC1LPE445": "Q10E",
  "QC1LPE455": "Q10E",
  "QC1LPE465": "Q10E",
  "QC1LPE475": "Q10E",
  "QC1LPE485": "Q10E",
  "QC1LPE495": "Q10E",
  "QC1LPE505": "Q10E",
  "QC1LPE515": "Q10E",
  "QC1LPE525": "Q10E",
  "MQC1LE": "BPME",
  "QC1LPE535": "Q10E",
  "QC1LPE545": "Q10E",
  "QC1LPE555": "Q10E",
  "QC1LPE565": "Q10E",
  "QC1LPE575": "Q10E",
  "QC1LPE585": "Q10E",
  "QC1LPE595": "Q10E",
  "QC1LE605": "Q10E",
  "QC1LE615": "Q10E",
  "QC1LE625": "Q10E",
  "QC1LE635": "Q10E",
  "QC1LE645": "Q10E",
  "QC1LE655": "Q10E",
  "QC1LE665": "Q10E",
  "QC1LE675": "Q10E",
  "QC1LE685": "Q10E",
  "QC1LE695": "Q10E",
  "QC1LE705": "Q10E",
  "QC1LE715": "Q10E",
  "QC1LE725": "Q10E",
  "QC1LE735": "Q10E",
  "QC1LE745": "Q10E",
  "QC1LE755": "Q10E",
  "QC1LE765": "Q10E",
  "QC1LE775": "Q10E",
  "QC1LE785": "Q10E",
  "QC1LE795": "Q10E",
  "QC1LE805": "Q10E",
  "QC1LE815": "Q10E",
  "QC1LE825": "Q10E",
  "QC1LE835": "Q10E",
  "QC1LE845": "Q10E",
  "QC1LE855": "Q10E",
  "QC1LE865": "Q10E",
  "QC1LE875": "Q10E",
  "QC1LE885": "Q10E",
  "QC1LE895": "Q10E",
  "QC1LE905": "Q10E",
  "QC1LE915": "Q10E",
  "QC1LE925": "Q10E",
  "QC1LE935": "Q10E",
  "QC1LE945": "Q10E",
  "QC1LE955": "Q10E",
  "QC1LE965": "Q10E",
  "QC1LE975": "Q10E",
  "QC1LE985": "Q10E",
  "QC1LE995": "Q10E",
  "QC1LE1005": "Q10E",
  "QC1LE1015": "Q10E",
  "QC1LE1025": "Q10E",
  "QC1LE1035": "Q10E",
  "QC1LE1045": "Q10E",
  "QC1LE1055": "Q10E",
  "QC1LE1065": "Q10E",
  "QC1LE1075": "Q10E",
  "QC1LE1085": "Q10E",
  "QC1LE1095": "Q10E",
  "QC1LE1105": "Q10E",
  "QC1LE1115": "Q10E",
  "QC1LE1125": "Q10E",
  "QC1LE1135": "Q10E",
  "QC1LE1145": "Q10E",
  "QC1LE1155": "Q10E",
  "QC1LE1165": "Q10E",
  "QC1LE1175": "Q10E",
  "QC1LE1185": "Q10E",
  "QC1LE1195": "Q10E",
  "QC1LE1205": "Q10E",
  "QC1LE1215": "Q10E",
  "QC1LE1225": "Q10E",
  "QC1LE1235": "Q10E",
  "QC1LE1245": "Q10E",
  "QC1LE1255": "Q10E",
  "QC1LE1265": "Q10E",
  "QC1LE1275": "Q10E",
  "QC1LE1285": "Q10E",
  "QC1LE1295": "Q10E",
  "QC1LE1305": "Q10E",
  "QC1LE1315": "Q10E",
  "QC1LE1325": "Q10E",
  "QC1LE1335": "Q10E",
  "QC1LE1345": "Q10E",
  "QC1LE1355": "Q10E",
  "QC1LE1365": "Q10E",
  "QC1LE1375": "Q10E",
  "QC1LE1385": "Q10E",
  "QC1LE1395": "Q10E",
  "QC1LE1405": "Q10E",
  "QC1LE1415": "Q10E",
  "QC1LE1425": "Q10E",
  "QC1LE1435": "Q10E",
  "QC1LE1445": "Q10E",
  "QC1LE1455": "Q10E",
  "QC1LE1465": "Q10E",
  "QC1LE1475": "Q10E",
  "QC1LE1485": "Q10E",
  "QC1LE1495": "Q10E",
  "QC1LE1505": "Q10E",
  "QC1LE1515": "Q10E",
  "QC1LE1525": "Q10E",
  "QC1LE1535": "Q10E",
  "QC1LE1545": "Q10E",
  "QC1LE1555": "Q10E",
  "QC1LE1565": "Q10E",
  "QC1LE1575": "Q10E",
  "QC1LE1585": "Q10E",
  "QC1LE1595": "Q10E",
  "QC1LE1605": "Q10E",
  "QC1LE1615": "Q10E",
  "QC1LE1625": "Q10E",
  "QC1LE1635": "Q10E",
  "QC1LE1645": "Q10E",
  "QC1LE1655": "Q10E",
  "QC1LE1665": "Q10E",
  "QC1LE1675": "Q10E",
  "QC1LE1685": "Q10E",
  "QC1LE1695": "Q10E",
  "QC1LE1705": "Q10E",
  "QC1LE1715": "Q10E",
  "QC1LE1725": "Q10E",
  "QC1LE1735": "Q10E",
  "QC1LE1745": "Q10E",
  "QC1LE1755": "Q10E",
  "QC1LE1765": "Q10E",
  "QC1LE1775": "Q10E",
  "QC1LE1785": "Q10E",
  "QC1LE1795": "Q10E",
  "QC1LE1805": "Q10E",
  "QC1LE1815": "Q10E",
  "QC1LE1825": "Q10E",
  "QC1LE1835": "Q10E",
  "QC1LE1845": "Q10E",
  "QC1LE1855": "Q10E",
  "QC1LE1865": "Q10E",
  "QC1LE1875": "Q10E",
  "QC1LE1885": "Q10E",
  "QC1LE1895": "Q10E",
  "QC2LE1905": "QC10E",
  "QC2LE1915": "QC10E",
  "QC2LE1925": "QC10E",
  "QC2LE1935": "QC10E",
  "QC2LE1945": "QC10E",
  "QC2LE1955": "QC10E",
  "QC2LE1965": "QC10E",
  "QC2LE1975": "QC10E",
  "QC2LE1985": "QC10E",
  "QC2LE1995": "QC10E",
  "QC2LE2005": "QC10E",
  "QC2LE2015": "QC10E",
  "QC2LE2025": "QC10E",
  "QC2LE2035": "QC10E",
  "QC2LE2045": "QC10E",
  "QC2LE2055": "QC10E",
  "QC2LE2065": "QC10E",
  "QC2LE2075": "QC10E",
  "QC2LE2085": "QC10E",
  "QC2LE2095": "QC10E",
  "QC2LE2105": "QC10E",
  "QC2LE2115": "QC10E",
  "QC2LE2125": "QC10E",
  "QC2LE2135": "QC10E",
  "QC2LE2145": "QC10E",
  "QC2LE2155": "QC10E",
  "QC2LE2165": "QC10E",
  "QC2LE2175": "QC10E",
  "QC2LE2185": "QC10E",
  "QC2LE2195": "QC10E",
  "QC2LE2205": "QC10E",
  "QC2LE2215": "QC10E",
  "QC2LE2225": "QC10E",
  "QC2LE2235": "QC10E",
  "QC2LE2245": "QC10E",
  "MQC2LE": "BPME",
  "QC2LE2255": "QC10E",
  "QC2LE2265": "QC10E",
  "QC2LE2275": "QC10E",
  "QC2LE2285": "QC10E",
  "QC2LE2295": "QC10E",
  "QC2LE2305": "QC10E",
  "QC2LE2315": "QC10E",
  "QC2LE2325": "QC10E",
  "QC2LE2335": "QC10E",
  "QC2LE2345": "QC10E",
  "QC2LE2355": "QC10E",
  "QC2LE2365": "QC10E",
  "QC2LE2375": "QC10E",
  "QC2LE2385": "QC10E",
  "QC2LE2395": "QC10E",
  "QC2LE2405": "QC10E",
  "QC2LE2415": "QC10E",
  "QC2LE2425": "QC10E",
  "QC2LE2435": "QC10E",
  "QC2LE2445": "QC10E",
  "QC2LE2455": "QC10E",
  "QC2LE2465": "QC10E",
  "QC2LE2475": "QC10E",
  "QC2LE2485": "QC10E",
  "QC2LE2495": "QC10E",
  "QC2LE2505": "QC10E",
  "QC2LE2515": "QC10E",
  "QC2LE2525": "QC10E",
  "QC2LE2535": "QC10E",
  "QC2LE2545": "QC10E",
  "QC2LE2555": "QC10E",
  "QC2LE2565": "QC10E",
  "QC2LE2575": "QC10E",
  "QC2LE2585": "QC10E",
  "QC2LE2595": "QC10E",
  "QC2LE2605": "QC10E",
  "QC2LE2615": "QC10E",
  "QC2LE2625": "QC10E",
  "QC2LE2635": "QC10E",
  "QC2LE2645": "QC10E",
  "QC2LE2655": "QC10E",
  "QC2LE2665": "QC10E",
  "QC2LE2675": "QC10E",
  "QC2LE2685": "QC10E",
  "QC2LE2695": "QC10E",
  "QC2LE2705": "QC10E",
  "QC2LE2715": "QC10E",
  "QC2LE2725": "QC10E",
  "QC2LE2735": "QC10E",
  "QC2LE2745": "QC10E",
  "QC2LE2755": "QC10E",
  "QC2LE2765": "QC10E",
  "QC2LE2775": "QC10E",
  "QC2LE2785": "QC10E",
  "QC2LE2795": "QC10E",
  "QC2LE2805": "QC10E",
  "QC2LE2815": "QC10E",
  "QC2LE2825": "QC10E",
  "QC2LE2835": "QC10E",
  "QC2LE2845": "QC10E",
  "QC2LE2855": "QC10E",
  "QC2LE2865": "QC10E",
  "QC2LE2875": "QC10E",
  "QC2LE2885": "QC10E",
  "QC2LE2895": "QC10E",
  "QC2LE2905": "QC10E",
  "QC2LE2915": "QC10E",
  "QC2LE2925": "QC10E",
  "QC2LE2935": "QC10E",
  "QC2LE2945": "QC10E",
  "QC2LE2955": "QC10E",
  "QC2LE2965": "QC10E",
  "QC2LE2975": "QC10E",
  "QC2LE2985": "QC10E",
  "QC2LE2995": "QC10E",
  "QC2LE3005": "QC10E",
  "QC2LE3015": "QC10E",
  "QC2LE3025": "QC10E",
  "QC2LE3035": "QC10E",
  "QC2LE3045": "QC10E",
  "QC2LE3055": "QC10E",
  "QC2LE3065": "QC10E",
  "QC2LE3075": "QC10E",
  "QC2LE3085": "QC10E",
  "QC2LE3095": "QC10E",
  "QC2LE3105": "QC10E",
  "QC2LE3115": "QC10E",
  "QC2LE3125": "QC10E",
  "QC2LE3135": "QC10E",
  "QC2LE3145": "QC10E",
  "QC2LE3155": "QC10E",
  "QC2LE3165": "QC10E",
  "QC2LE3175": "QC10E",
  "QC2LE3185": "QC10E",
  "QC2LE3195": "QC10E",
  "QC2LE3205": "QC10E",
  "QC2LE3215": "QC10E",
  "QC2LE3225": "QC10E",
  "QC2LE3235": "QC10E",
  "QC2LE3245": "QC10E",
  "QC2LE3255": "QC10E",
  "QC2LE3265": "QC10E",
  "QC2LE3275": "QC10E",
  "QC2LE3285": "QC10E",
  "QC2LE3295": "QC10E",
  "QC2LE3305": "QC10E",
  "QC2LE3315": "QC10E",
  "QC2LE3325": "QC10E",
  "QC2LE3335": "QC10E",
  "QC2LE3345": "QC10E",
  "QC2LE3355": "QC10E",
  "QC2LE3365": "QC10E",
  "QC2LE3375": "QC10E",
  "QC2LE3385": "QC10E",
  "QC2LE3395": "QC10E",
  "QC2LE3405": "QC10E",
  "QC2LE3415": "QC10E",
  "QC2LE3425": "QC10E",
  "QC2LE3435": "QC10E",
  "QC2LE3445": "QC10E",
  "QC2LE3455": "QC10E",
  "QC2LE3465": "QC10E",
  "QC2LE3475": "QC10E",
  "QC2LE3485": "QC10E",
  "QC2LE3495": "QC10E",
  "QKALE": "QKnewE",
  "ZHQLC2LE": "STHLC2LE",
  "MQLC2LE": "BPME",
  "QLC2LE": "Q560newiE",
  "QKBLE": "QKnewE",
  "BLC1LE": "BLC1LE",
  "QKCLE": "QKnewE",
  "QLC3LE": "Q560newE",
  "MQLC3LE": "BPME",
  "BC1LE": "BC344E",
  "ZVF1LE": "STVFB279E",
  "ZHF1LE": "STH2E",
  "BC2LE": "BC344E",
  "QLC4LE": "Q560newE",
  "MQLC4LE": "BPME",
  "ZHQLC4LE": "STHE",
  "ZVF2LE": "STVFB279E",
  "ZHF2LE": "STH2E",
  "MQLC5LE": "BPME",
  "QLC5LE": "Q560newE",
  "BC3LE": "BC344E",
  "BC4LE": "BC344E",
  "QLC7LE": "Q560newE",
  "MQLC7LE": "BPME",
  "SLYTLE1": "S600E",
  "QLY1LE.1": "Q460E",
  "MQLY1LE1": "BPME",
  "ZVQLY1LE1": "STV287E",
  "ZVQLY2LE1": "STV287E",
  "MQLY2LE1": "BPME",
  "QLY2LE.1": "Q560newE",
  "BLY1LE.1": "B4000RE",
  "QLY3LE": "Q560newE",
  "MQLY3LE": "BPME",
  "BLY1LE.2": "B4000RE",
  "QLY2LE.2": "Q560newE",
  "MQLY2LE2": "BPME",
  "ZVQLY2LE2": "STV287E",
  "ZVQLY1LE2": "STV287E",
  "MQLY1LE2": "BPME",
  "QLY1LE.2": "Q460E",
  "SLYTLE2": "S600E",
  "MQLB1LE": "BPME",
  "QLB1LE": "Q560newE",
  "ZHQLB2LE": "STHE",
  "MQLB2LE": "BPME",
  "QLB2LE": "Q560newE",
  "BLB1LE": "B4000RE",
  "QLB3LE": "Q1120newE",
  "MQLB3LE": "BPME",
  "ZVQLB3LE": "STV287E",
  "ZVF3LE": "STVFB279E",
  "ZHQLB4LE": "STHE",
  "QLB4LE": "Q560newE",
  "MQLB4LE": "BPME",
  "SLXTLE.1": "S500E",
  "ZVQLX1LE1": "STV287E",
  "MQLX1LE1": "BPME",
  "QLX1LE.1": "Q560newE",
  "BLX2LE.1": "B4000E",
  "QLX2LE": "Q560newE",
  "MQLX2LE": "BPME",
  "BLX2LE.2": "B4000E",
  "QLX1LE.2": "Q560newE",
  "MQLX1LE2": "BPME",
  "ZVQLX1LE2": "STV287E",
  "SLXTLE.2": "S500E",
  "MQLA2LE": "BPME",
  "QLA2LE": "Q560newE",
  "ZHQLA2LE": "STHE",
  "QLA3LE": "Q560newE",
  "MQLA3LE": "BPME",
  "ZVQLA3LE": "STV287E",
  "ZVF4LE": "STVFB279E",
  "MQLA4LE": "BPME",
  "QLA4LE": "Q557E",
  "BLA2LE": "B5907E",
  "QLA5LE": "Q826E",
  "MQLA5LE": "BPME",
  "ZVQLA5LE": "STV279E",
  "QLA6LE": "Q826E",
  "MQLA6LE": "BPME",
  "ZHQLA6LE": "STHE",
  "ZVQLA7LE": "STV279E",
  "MQLA7LE": "BPME",
  "QLA7LE": "Q826E",
  "BLA4LE.1": "B5907RE",
  "QLA8LE": "Q560newE",
  "MQLA8LE": "BPME",
  "BLA4LE.2": "B5907RE",
  "QLA9LE": "Q826E",
  "MQLA9LE": "BPME",
  "ZVQLA9LE": "STV279E",
  "ZHQLA10LE": "STHE",
  "MQLA10LE": "BPME",
  "QLA10LE": "Q826E",
  "MQF4E1": "BPME",
  "QF4E.1": "Q1015E",
  "ZHQF4E1": "STHE",
  "ZVQD3E1": "STV160E",
  "QD3E.1": "Q826E",
  "MQD3E1": "BPME",
  "SD3TLE.1": "S1030E",
  "B2E.4": "B5907E",
  "QF2E.1": "Q557E",
  "MQF2E1": "BPME",
  "ZHQF2E1": "STHE",
  "ZVQD1E1": "STV160E",
  "QD1E.1": "Q1015E",
  "MQD1E1": "BPME",
  "ZHQF2E2": "STHE",
  "MQF2E2": "BPME",
  "QF2E.2": "Q557E",
  "B2E.5": "B5907E",
  "SD3TLE.2": "S1030E",
  "MQD3E2": "BPME",
  "QD3E.2": "Q826E",
  "ZVQD3E2": "STV160E",
  "SKBTLE.1": "S344E",
  "ZHQF4E2": "STHE",
  "QF4E.2": "Q1015E",
  "MQF4E2": "BPME",
  "SF4TLE.1": "S334E",
  "ZHQEAE3": "STHE",
  "QEAE.3": "Q826E",
  "MQEAE3": "BPME",
  "ZVQD5E3": "STV160E",
  "QD5E.3": "Q826E",
  "MQD5E3": "BPME",
  "B2E.6": "B5907E",
  "MQF6E2": "BPME",
  "QF6E.2": "Q557E",
  "B2E.7": "B5907E",
  "MQD5E4": "BPME",
  "QD5E.4": "Q826E",
  "ZVQD5E4": "STV160E",
  "MQEAE4": "BPME",
  "QEAE.4": "Q826E",
  "ZHQEAE4": "STHE",
  "SF4TLE.2": "S334E",
  "MQF4E3": "BPME",
  "QF4E.3": "Q1015E",
  "ZHQF4E3": "STHE",
  "SKBTLE.2": "S344E",
  "ZVQD3E3": "STV160E",
  "QD3E.3": "Q826E",
  "MQD3E3": "BPME",
  "SD5TLE.1": "S1030E",
  "B2E.8": "B5907E",
  "QF2E.3": "Q557E",
  "MQF2E3": "BPME",
  "ZHQF2E3": "STHE",
  "ZVQD1E2": "STV160E",
  "QD1E.2": "Q1015E",
  "MQD1E2": "BPME",
  "ZHQF2E4": "STHE",
  "MQF2E4": "BPME",
  "QF2E.4": "Q557E",
  "B2E.9": "B5907E",
  "SD5TLE.2": "S1030E",
  "MQD3E4": "BPME",
  "QD3E.4": "Q826E",
  "ZVQD3E4": "STV160E",
  "SKCTLE.1": "S344E",
  "ZHQF4E4": "STHE",
  "QF4E.4": "Q1015E",
  "MQF4E4": "BPME",
  "SF6TLE.1": "S334E",
  "ZHQEAE5": "STHE",
  "QEAE.5": "Q826E",
  "MQEAE5": "BPME",
  "ZVQD5E5": "STV160E",
  "QD5E.5": "Q826E",
  "MQD5E5": "BPME",
  "B2E.10": "B5907E",
  "MQF6E3": "BPME",
  "QF6E.3": "Q557E",
  "B2E.11": "B5907E",
  "MQD5E6": "BPME",
  "QD5E.6": "Q826E",
  "ZVQD5E6": "STV160E",
  "MQEAE6": "BPME",
  "QEAE.6": "Q826E",
  "ZHQEAE6": "STHE",
  "SF6TLE.2": "S334E",
  "MQF4E5": "BPME",
  "QF4E.5": "Q1015E",
  "ZHQF4E5": "STHE",
  "SKCTLE.2": "S344E",
  "ZVQD3E5": "STV160E",
  "QD3E.5": "Q826E",
  "MQD3E5": "BPME",
  "SD7TLE.1": "S1030E",
  "B2E.12": "B5907E",
  "QF2E.5": "Q557E",
  "MQF2E5": "BPME",
  "ZHQF2E5": "STHE",
  "ZVQD1E3": "STV160E",
  "QD1E.3": "Q1015E",
  "MQD1E3": "BPME",
  "ZHQF2E6": "STHE",
  "MQF2E6": "BPME",
  "QF2E.6": "Q557E",
  "B2E.13": "B5907E",
  "SD7TLE.2": "S1030E",
  "MQT1TNE1": "BPME",
  "QT1TNE.1": "Q826E",
  "ZVQT1TNE1": "STV160E",
  "ZVQT2TNE1": "STV160E",
  "QT2TNE.1": "Q1015E",
  "MQT2TNE1": "BPME",
  "SF8TNE.1": "S334E",
  "ZHQTATNE1": "STHE",
  "QTATNE.1": "Q826E",
  "MQTATNE1": "BPME",
  "ZVQT3TNE1": "STV160E",
  "QT3TNE.1": "Q826E",
  "MQT3TNE1": "BPME",
  "B2E.14": "B5907E",
  "MQT4TNE1": "BPME",
  "QT4TNE.1": "Q826E",
  "ZVQT4TNE1": "STV160E",
  "MQTBTNE1": "BPME",
  "QTBTNE.1": "Q826newE",
  "ZHQTBTNE1": "STHE",
  "MQT5TNE": "BPME",
  "QT5TNE": "Q826E",
  "ZVQT5TNE": "STV160E",
  "ZHQTBTNE2": "STHE",
  "QTBTNE.2": "Q826newE",
  "MQTBTNE2": "BPME",
  "ZVQT4TNE2": "STV160E",
  "QT4TNE.2": "Q826E",
  "MQT4TNE2": "BPME",
  "B2E.15": "B5907E",
  "MQT3TNE2": "BPME",
  "QT3TNE.2": "Q826E",
  "ZVQT3TNE2": "STV160E",
  "MQTATNE2": "BPME",
  "QTATNE.2": "Q826E",
  "ZHQTATNE2": "STHE",
  "SF8TNE.2": "S334E",
  "MQT2TNE2": "BPME",
  "QT2TNE.2": "Q1015E",
  "ZVQT2TNE2": "STV160E",
  "ZVQT1TNE2": "STV160E",
  "QT1TNE.2": "Q826E",
  "MQT1TNE2": "BPME",
  "SD7NRE.1": "S1030E",
  "B2E.16": "B5907E",
  "QF2E.7": "Q557E",
  "MQF2E7": "BPME",
  "ZHQF2E7": "STHE",
  "ZVQD1E4": "STV160E",
  "QD1E.4": "Q1015E",
  "MQD1E4": "BPME",
  "ZHQF2E8": "STHE",
  "MQF2E8": "BPME",
  "QF2E.8": "Q557E",
  "B2E.17": "B5907E",
  "SD7NRE.2": "S1030E",
  "MQD3E6": "BPME",
  "QD3E.6": "Q826E",
  "ZVQD3E6": "STV160E",
  "SKCNRE.1": "S344E",
  "ZHQF4E6": "STHE",
  "QF4E.6": "Q1015E",
  "MQF4E6": "BPME",
  "SF6NRE.1": "S334E",
  "ZHQEAE7": "STHE",
  "QEAE.7": "Q826E",
  "MQEAE7": "BPME",
  "ZVQD5E7": "STV160E",
  "QD5E.7": "Q826E",
  "MQD5E7": "BPME",
  "B2E.18": "B5907E",
  "MQF6E4": "BPME",
  "QF6E.4": "Q557E",
  "B2E.19": "B5907E",
  "MQD5E8": "BPME",
  "QD5E.8": "Q826E",
  "ZVQD5E8": "STV160E",
  "MQEAE8": "BPME",
  "QEAE.8": "Q826E",
  "ZHQEAE8": "STHE",
  "SF6NRE.2": "S334E",
  "MQF4E7": "BPME",
  "QF4E.7": "Q1015E",
  "ZHQF4E7": "STHE",
  "SKCNRE.2": "S344E",
  "ZVQD3E7": "STV160E",
  "QD3E.7": "Q826E",
  "MQD3E7": "BPME",
  "SD5NRE.1": "S1030E",
  "B2E.20": "B5907E",
  "QF2E.9": "Q557E",
  "MQF2E9": "BPME",
  "ZHQF2E9": "STHE",
  "ZVQD1E5": "STV160E",
  "QD1E.5": "Q1015E",
  "MQD1E5": "BPME",
  "ZHQF2E10": "STHE",
  "MQF2E10": "BPME",
  "QF2E.10": "Q557E",
  "B2E.21": "B5907E",
  "SD5NRE.2": "S1030E",
  "MQD3E8": "BPME",
  "QD3E.8": "Q826E",
  "ZVQD3E8": "STV160E",
  "SKBNRE.1": "S344E",
  "ZHQF4E8": "STHE",
  "QF4E.8": "Q1015E",
  "MQF4E8": "BPME",
  "SF4NRE.1": "S334E",
  "ZHQEAE9": "STHE",
  "QEAE.9": "Q826E",
  "MQEAE9": "BPME",
  "ZVQD5E9": "STV160E",
  "QD5E.9": "Q826E",
  "MQD5E9": "BPME",
  "B2E.22": "B5907E",
  "MQF6E5": "BPME",
  "QF6E.5": "Q557E",
  "B2E.23": "B5907E",
  "MQD5E10": "BPME",
  "QD5E.10": "Q826E",
  "ZVQD5E10": "STV160E",
  "MQEAE10": "BPME",
  "QEAE.10": "Q826E",
  "ZHQEAE10": "STHE",
  "SF4NRE.2": "S334E",
  "MQF4E9": "BPME",
  "QF4E.9": "Q1015E",
  "ZHQF4E9": "STHE",
  "SKBNRE.2": "S344E",
  "ZVQD3E9": "STV160E",
  "QD3E.9": "Q826E",
  "MQD3E9": "BPME",
  "SD3NRE.1": "S1030E",
  "B2E.24": "B5907E",
  "QF2E.11": "Q557E",
  "MQF2E11": "BPME",
  "ZHQF2E11": "STHE",
  "ZVQD1E6": "STV160E",
  "QD1E.6": "Q1015E",
  "MQD1E6": "BPME",
  "ZHQF2E12": "STHE",
  "MQF2E12": "BPME",
  "QF2E.12": "Q557E",
  "B2E.25": "B5907E",
  "SD3NRE.2": "S1030E",
  "MQD3E10": "BPME",
  "QD3E.10": "Q826E",
  "ZVQD3E10": "STV160E",
  "ZHQF4E10": "STHE",
  "QF4E.10": "Q1015E",
  "MQF4E10": "BPME",
  "SF2NRE.1": "S334E",
  "ZHQEAE11": "STHE",
  "QEAE.11": "Q826E",
  "MQEAE11": "BPME",
  "ZVQD5E11": "STV160E",
  "QD5E.11": "Q826E",
  "MQD5E11": "BPME",
  "B2E.26": "B5907E",
  "MQF6E6": "BPME",
  "QF6E.6": "Q557E",
  "B2E.27": "B5907E",
  "MQD5E12": "BPME",
  "QD5E.12": "Q826E",
  "ZVQD5E12": "STV160E",
  "MQEAE12": "BPME",
  "QEAE.12": "Q826E",
  "ZHQEAE12": "STHE",
  "SF2NRE.2": "S334E",
  "MQS4NE1": "BPME",
  "QS4NE.1": "Q826E",
  "ZHQS4NE1": "STHE",
  "ZVQSBNE1": "STV160E",
  "QSBNE.1": "Q826E",
  "MQSBNE1": "BPME",
  "MQS3NE1": "BPME",
  "QS3NE.1": "Q826E",
  "B2E.28": "B5907E",
  "MQS2NE1": "BPME",
  "QS2NE.1": "Q557E",
  "BSWNRE": "B2900E",
  "MQR7NE1": "BPME",
  "QR7NE.1": "Q826E",
  "ZVQR7NE1": "STV160E",
  "ZHQR6NE1": "STHE",
  "QR6NE.1": "Q1015E",
  "MQR6NE1": "BPME",
  "ZVQR5NE1": "STV210E",
  "QR5NE.1": "Q1080E",
  "MQR5NE1": "BPME",
  "ZHQR4NE1": "STHE",
  "QR4NE.1": "Q1080E",
  "MQR4NE1": "BPME",
  "ZVQR3NE1": "STV210E",
  "QR3NE.1": "Q1080E",
  "MQR3NE1": "BPME",
  "ZHQR2NE1": "STHE",
  "QR2NE.1": "Q1080E",
  "MQR2NE1": "BPME",
  "ZVQDRNE1": "STV210E",
  "QDRNE.1": "Q1080E",
  "MQDRNE1": "BPME",
  "ZHQFRNE1": "STHE",
  "QFRNE.1": "Q1080E",
  "MQFRNE1": "BPME",
  "ZVQDRNE2": "STV210E",
  "QDRNE.2": "Q1080E",
  "MQDRNE2": "BPME",
  "ZHQFRNE2": "STHE",
  "QFRNE.2": "Q1080E",
  "MQFRNE2": "BPME",
  "ZVQDRNE3": "STV210E",
  "QDRNE.3": "Q1080E",
  "MQDRNE3": "BPME",
  "ZHQFRNE3": "STHE",
  "QFRNE.3": "Q1080E",
  "MQFRNE3": "BPME",
  "ZVQDRNE4": "STV210E",
  "QDRNE.4": "Q1080E",
  "MQDRNE4": "BPME",
  "ZHQFRNE4": "STHE",
  "QFRNE.4": "Q1080E",
  "MQFRNE4": "BPME",
  "ZVQDRNE5": "STV210E",
  "QDRNE.5": "Q1080E",
  "MQDRNE5": "BPME",
  "ZHQFRNE5": "STHE",
  "QFRNE.5": "Q1080E",
  "MQFRNE5": "BPME",
  "ZVQDRNE6": "STV210E",
  "QDRNE.6": "Q1080E",
  "MQDRNE6": "BPME",
  "ZHQR2NE2": "STHE",
  "QR2NE.2": "Q1080E",
  "MQR2NE2": "BPME",
  "ZVQR3NE2": "STV210E",
  "QR3NE.2": "Q1080E",
  "MQR3NE2": "BPME",
  "ZHQR4NE2": "STHE",
  "QR4NE.2": "Q1080E",
  "MQR4NE2": "BPME",
  "ZVQR5NE2": "STV210E",
  "QR5NE.2": "Q1080E",
  "MQR5NE2": "BPME",
  "MQR6NE2": "BPME",
  "QR6NE.2": "Q1015E",
  "ZHQR6NE2": "STHE",
  "ZVQR7NE2": "STV160E",
  "QR7NE.2": "Q826E",
  "MQR7NE2": "BPME",
  "BSWNLE": "B2900E",
  "MQS2NE2": "BPME",
  "QS2NE.2": "Q557E",
  "B2E.29": "B5907E",
  "QS3NE.2": "Q826E",
  "MQS3NE2": "BPME",
  "MQSBNE2": "BPME",
  "QSBNE.2": "Q826E",
  "ZVQSBNE2": "STV160E",
  "ZHQS4NE2": "STHE",
  "QS4NE.2": "Q826E",
  "MQS4NE2": "BPME",
  "SF2NLE.1": "S334E",
  "ZHQEAE13": "STHE",
  "QEAE.13": "Q826E",
  "MQEAE13": "BPME",
  "ZVQD5E13": "STV160E",
  "QD5E.13": "Q826E",
  "MQD5E13": "BPME",
  "B2E.30": "B5907E",
  "MQF6E7": "BPME",
  "QF6E.7": "Q557E",
  "B2E.31": "B5907E",
  "MQD5E14": "BPME",
  "QD5E.14": "Q826E",
  "ZVQD5E14": "STV160E",
  "MQEAE14": "BPME",
  "QEAE.14": "Q826E",
  "ZHQEAE14": "STHE",
  "SF2NLE.2": "S334E",
  "MQF4E11": "BPME",
  "QF4E.11": "Q1015E",
  "ZHQF4E11": "STHE",
  "ZVQD3E11": "STV160E",
  "QD3E.11": "Q826E",
  "MQD3E11": "BPME",
  "SD3NLE.1": "S1030E",
  "B2E.32": "B5907E",
  "QF2E.13": "Q557E",
  "MQF2E13": "BPME",
  "ZHQF2E13": "STHE",
  "ZVQD1E7": "STV160E",
  "QD1E.7": "Q1015E",
  "MQD1E7": "BPME",
  "ZHQF2E14": "STHE",
  "MQF2E14": "BPME",
  "QF2E.14": "Q557E",
  "B2E.33": "B5907E",
  "SD3NLE.2": "S1030E",
  "MQD3E12": "BPME",
  "QD3E.12": "Q826E",
  "ZVQD3E12": "STV160E",
  "SKBNLE.1": "S344E",
  "ZHQF4E12": "STHE",
  "QF4E.12": "Q1015E",
  "MQF4E12": "BPME",
  "SF4NLE.1": "S334E",
  "ZHQEAE15": "STHE",
  "QEAE.15": "Q826E",
  "MQEAE15": "BPME",
  "ZVQD5E15": "STV160E",
  "QD5E.15": "Q826E",
  "MQD5E15": "BPME",
  "B2E.34": "B5907E",
  "MQF6E8": "BPME",
  "QF6E.8": "Q557E",
  "B2E.35": "B5907E",
  "MQD5E16": "BPME",
  "QD5E.16": "Q826E",
  "ZVQD5E16": "STV160E",
  "MQEAE16": "BPME",
  "QEAE.16": "Q826E",
  "ZHQEAE16": "STHE",
  "SF4NLE.2": "S334E",
  "MQF4E13": "BPME",
  "QF4E.13": "Q1015E",
  "ZHQF4E13": "STHE",
  "SKBNLE.2": "S344E",
  "ZVQD3E13": "STV160E",
  "QD3E.13": "Q826E",
  "MQD3E13": "BPME",
  "SD5NLE.1": "S1030E",
  "B2E.36": "B5907E",
  "QF2E.15": "Q557E",
  "MQF2E15": "BPME",
  "ZHQF2E15": "STHE",
  "ZVQD1E8": "STV160E",
  "QD1E.8": "Q1015E",
  "MQD1E8": "BPME",
  "ZHQF2E16": "STHE",
  "MQF2E16": "BPME",
  "QF2E.16": "Q557E",
  "B2E.37": "B5907E",
  "SD5NLE.2": "S1030E",
  "MQD3E14": "BPME",
  "QD3E.14": "Q826E",
  "ZVQD3E14": "STV160E",
  "SKCNLE.1": "S344E",
  "ZHQF4E14": "STHE",
  "QF4E.14": "Q1015E",
  "MQF4E14": "BPME",
  "SF6NLE.1": "S334E",
  "ZHQEAE17": "STHE",
  "QEAE.17": "Q826E",
  "MQEAE17": "BPME",
  "ZVQD5E17": "STV160E",
  "QD5E.17": "Q826E",
  "MQD5E17": "BPME",
  "B2E.38": "B5907E",
  "MQF6E9": "BPME",
  "QF6E.9": "Q557E",
  "B2E.39": "B5907E",
  "MQD5E18": "BPME",
  "QD5E.18": "Q826E",
  "ZVQD5E18": "STV160E",
  "MQEAE18": "BPME",
  "QEAE.18": "Q826E",
  "ZHQEAE18": "STHE",
  "SF6NLE.2": "S334E",
  "MQF4E15": "BPME",
  "QF4E.15": "Q1015E",
  "ZHQF4E15": "STHE",
  "SKCNLE.2": "S344E",
  "ZVQD3E15": "STV160E",
  "QD3E.15": "Q826E",
  "MQD3E15": "BPME",
  "SD7NLE.1": "S1030E",
  "B2E.40": "B5907E",
  "QF2E.17": "Q557E",
  "MQF2E17": "BPME",
  "ZHQF2E17": "STHE",
  "ZVQD1E9": "STV160E",
  "QD1E.9": "Q1015E",
  "MQD1E9": "BPME",
  "ZHQF2E18": "STHE",
  "MQF2E18": "BPME",
  "QF2E.18": "Q557E",
  "B2E.41": "B5907E",
  "SD7NLE.2": "S1030E",
  "MQT1NFE1": "BPME",
  "QT1NFE.1": "Q826E",
  "ZVQT1NFE1": "STV160E",
  "ZVQT2NFE1": "STV160E",
  "QT2NFE.1": "Q1015E",
  "MQT2NFE1": "BPME",
  "SF8NFE.1": "S334E",
  "ZHQTANFE1": "STHE",
  "QTANFE.1": "Q826E",
  "MQTANFE1": "BPME",
  "ZVQT3NFE1": "STV160E",
  "QT3NFE.1": "Q826E",
  "MQT3NFE1": "BPME",
  "B2E.42": "B5907E",
  "MQT4NFE1": "BPME",
  "QT4NFE.1": "Q826E",
  "ZVQT4NFE1": "STV160E",
  "MQTBNFE1": "BPME",
  "QTBNFE.1": "Q826newE",
  "ZHQTBNFE1": "STHE",
  "MQT5NFE": "BPME",
  "QT5NFE": "Q826E",
  "ZVQT5NFE": "STV160E",
  "ZHQTBNFE2": "STHE",
  "QTBNFE.2": "Q826newE",
  "MQTBNFE2": "BPME",
  "ZVQT4NFE2": "STV160E",
  "QT4NFE.2": "Q826E",
  "MQT4NFE2": "BPME",
  "B2E.43": "B5907E",
  "MQT3NFE2": "BPME",
  "QT3NFE.2": "Q826E",
  "ZVQT3NFE2": "STV160E",
  "MQTANFE2": "BPME",
  "QTANFE.2": "Q826E",
  "ZHQTANFE2": "STHE",
  "SF8NFE.2": "S334E",
  "MQT2NFE2": "BPME",
  "QT2NFE.2": "Q1015E",
  "ZVQT2NFE2": "STV160E",
  "ZVQT1NFE2": "STV160E",
  "QT1NFE.2": "Q826E",
  "MQT1NFE2": "BPME",
  "SD7FRE.1": "S1030E",
  "B2E.44": "B5907E",
  "QF2E.19": "Q557E",
  "MQF2E19": "BPME",
  "ZHQF2E19": "STHE",
  "ZVQD1E10": "STV160E",
  "QD1E.10": "Q1015E",
  "MQD1E10": "BPME",
  "ZHQF2E20": "STHE",
  "MQF2E20": "BPME",
  "QF2E.20": "Q557E",
  "B2E.45": "B5907E",
  "SD7FRE.2": "S1030E",
  "MQD3E16": "BPME",
  "QD3E.16": "Q826E",
  "ZVQD3E16": "STV160E",
  "SKCFRE.1": "S344E",
  "ZHQF4E16": "STHE",
  "QF4E.16": "Q1015E",
  "MQF4E16": "BPME",
  "SF6FRE.1": "S334E",
  "ZHQEAE19": "STHE",
  "QEAE.19": "Q826E",
  "MQEAE19": "BPME",
  "ZVQD5E19": "STV160E",
  "QD5E.19": "Q826E",
  "MQD5E19": "BPME",
  "B2E.46": "B5907E",
  "MQF6E10": "BPME",
  "QF6E.10": "Q557E",
  "B2E.47": "B5907E",
  "MQD5E20": "BPME",
  "QD5E.20": "Q826E",
  "ZVQD5E20": "STV160E",
  "MQEAE20": "BPME",
  "QEAE.20": "Q826E",
  "ZHQEAE20": "STHE",
  "SF6FRE.2": "S334E",
  "MQF4E17": "BPME",
  "QF4E.17": "Q1015E",
  "ZHQF4E17": "STHE",
  "SKCFRE.2": "S344E",
  "ZVQD3E17": "STV160E",
  "QD3E.17": "Q826E",
  "MQD3E17": "BPME",
  "SD5FRE.1": "S1030E",
  "B2E.48": "B5907E",
  "QF2E.21": "Q557E",
  "MQF2E21": "BPME",
  "ZHQF2E21": "STHE",
  "ZVQD1E11": "STV160E",
  "QD1E.11": "Q1015E",
  "MQD1E11": "BPME",
  "ZHQF2E22": "STHE",
  "MQF2E22": "BPME",
  "QF2E.22": "Q557E",
  "B2E.49": "B5907E",
  "SD5FRE.2": "S1030E",
  "MQD3E18": "BPME",
  "QD3E.18": "Q826E",
  "ZVQD3E18": "STV160E",
  "SKBFRE.1": "S344E",
  "ZHQF4E18": "STHE",
  "QF4E.18": "Q1015E",
  "MQF4E18": "BPME",
  "SF4FRE.1": "S334E",
  "ZHQEAE21": "STHE",
  "QEAE.21": "Q826E",
  "MQEAE21": "BPME",
  "ZVQD5E21": "STV160E",
  "QD5E.21": "Q826E",
  "MQD5E21": "BPME",
  "B2E.50": "B5907E",
  "MQF6E11": "BPME",
  "QF6E.11": "Q557E",
  "B2E.51": "B5907E",
  "MQD5E22": "BPME",
  "QD5E.22": "Q826E",
  "ZVQD5E22": "STV160E",
  "MQEAE22": "BPME",
  "QEAE.22": "Q826E",
  "ZHQEAE22": "STHE",
  "SF4FRE.2": "S334E",
  "MQF4E19": "BPME",
  "QF4E.19": "Q1015E",
  "ZHQF4E19": "STHE",
  "SKBFRE.2": "S344E",
  "ZVQD3E19": "STV160E",
  "QD3E.19": "Q826E",
  "MQD3E19": "BPME",
  "SD3FRE.1": "S1030E",
  "B2E.52": "B5907E",
  "QF2E.23": "Q557E",
  "MQF2E23": "BPME",
  "ZHQF2E23": "STHE",
  "ZVQD1E12": "STV160E",
  "QD1E.12": "Q1015E",
  "MQD1E12": "BPME",
  "ZHQF2E24": "STHE",
  "MQF2E24": "BPME",
  "QF2E.24": "Q557E",
  "B2E.53": "B5907E",
  "SD3FRE.2": "S1030E",
  "MQD3E20": "BPME",
  "QD3E.20": "Q826E",
  "ZVQD3E20": "STV160E",
  "ZHQF4E20": "STHE",
  "QF4E.20": "Q1015E",
  "MQF4E20": "BPME",
  "SF2FRE.1": "S334E",
  "ZHQEAE23": "STHE",
  "QEAE.23": "Q826E",
  "MQEAE23": "BPME",
  "ZVQD5E23": "STV160E",
  "QD5E.23": "Q826E",
  "MQD5E23": "BPME",
  "B2E.54": "B5907E",
  "MQF6E12": "BPME",
  "QF6E.12": "Q557E",
  "B2E.55": "B5907E",
  "MQD5E24": "BPME",
  "QD5E.24": "Q826E",
  "ZVQD5E24": "STV160E",
  "MQEAE24": "BPME",
  "QEAE.24": "Q826E",
  "ZHQEAE24": "STHE",
  "SF2FRE.2": "S334E",
  "MQS4FRE": "BPME",
  "QS4FRE": "Q826E",
  "ZVQS4FRE": "STV160E",
  "QSBFRE": "Q826E",
  "MQSBFRE": "BPME",
  "ZHQSBFRE": "STHE",
  "ZVQS3FRE": "STV160E",
  "MQS3FRE": "BPME",
  "QS3FRE": "Q826E",
  "B2E.56": "B5907E",
  "MQS2FRE": "BPME",
  "QS2FRE": "Q557E",
  "BSWFRE": "B891E",
  "QI7E": "Q1015E",
  "MQI7E": "BPME",
  "ZVQI7E": "STV160E",
  "MQI6E": "BPME",
  "QI6E": "Q1015E",
  "ZHQI6E": "STHE",
  "ZVQI5E": "STV160E",
  "QI5E": "Q1015E",
  "MQI5E": "BPME",
  "ZHQI4E": "STHE",
  "MQI4E": "BPME",
  "QI4E": "Q826E",
  "ZVQI3E": "STV160E",
  "QI3E": "Q1015E",
  "MQI3E": "BPME",
  "ZHQI2E": "STHE",
  "QI2E": "Q1015E",
  "MQI2E": "BPME",
  "FZDUMP1 (LFR035)": "HER_DUM_2000aE",
  "FZVALE": "HER_LAM_2000aE",
  "QX7RE": "Q1080E",
  "MQX7RE": "BPME",
  "ZVQX7RE": "STV160E",
  "ZHQX6RE": "STHE",
  "QX6RE": "Q1015E",
  "MQX6RE": "BPME",
  "SXABE.1": "SXAB334E",
  "FZVABE": "FZVAB350E",
  "FZHABE5.1": "FZHAB350E",
  "FZHABE5.2": "FZHAB350E",
  "FZHABE4.1": "FZHAB350E",
  "FZHABE4.2": "FZHAB350E",
  "ZVQX5RE": "STV160E",
  "QX5RE": "Q1015E",
  "MQX5RE": "BPME",
  "FZHABE3.1": "FZHAB350E",
  "FZHABE3.2": "FZHAB350E",
  "FZHABE2.1": "FZHAB350E",
  "FZHABE2.2": "FZHAB350E",
  "FZHABE1.1": "FZHAB350E",
  "FZHABE1.2": "FZHAB350E",
  "ZHQX4RE": "STHE",
  "QX4RE": "Q1015E",
  "MQX4RE": "BPME",
  "BX2E": "B5907E",
  "ZVQX3RE": "STV160E",
  "QX3RE": "Q1015E",
  "MQX3RE": "BPME",
  "ZHQX2RE": "STHE",
  "QX2RE": "Q816E",
  "MQX2RE": "BPME",
  "MQX2LE": "BPME",
  "QX2LE": "Q816E",
  "ZHQX2LE": "STHE",
  "MQX3LE": "BPME",
  "QX3LE": "Q1015E",
  "ZVQX3LE": "STV160E",
  "BX1E": "B5907E",
  "MQX4LE": "BPME",
  "QX4LE": "Q1015E",
  "ZHQX4LE": "STHE",
  "MQX5LE": "BPME",
  "QX5LE": "Q1015E",
  "ZVQX5LE": "STV160E",
  "FZLFBKE2": "FZLFBK1560E",
  "FZLFBKE1": "FZLFBK1560E",
  "SXABE.2": "SXAB334E",
  "MQX6LE": "BPME",
  "QX6LE": "Q1015E",
  "ZHQX6LE": "STHE",
  "FZDCCT (LFL029)": "FZDCCT500E",
  "FZCT (LFL030)": "FZCT500E",
  "MQX7LE": "BPME",
  "QX7LE": "Q1015E",
  "ZVQX7LE": "STV160E",
  "MQM2E": "BPME",
  "QM2E": "Q1015E",
  "ZHQM2E": "STHE",
  "MQM3E": "BPME",
  "QM3E": "Q1015E",
  "ZVQM3E": "STV160E",
  "FZTFBKE2": "FZTFBK550E",
  "FZTFBKE1": "FZTFBK550E",
  "MQM4E": "BPME",
  "QM4E": "Q1015E",
  "ZHQM4E": "STHE",
  "MQM5E": "BPME",
  "QM5E": "Q1015E",
  "ZVQM5E": "STV160E",
  "MQM6E": "BPME",
  "QM6E": "Q1015E",
  "ZHQM6E": "STHE",
  "MQM7E": "BPME",
  "QM7E": "Q1015E",
  "ZVQM7E": "STV160E",
  "BSWFLE": "B1239E",
  "MQS2FLE": "BPME",
  "QS2FLE": "Q557E",
  "B2E.57": "B5907E",
  "QS3FLE": "Q826E",
  "MQS3FLE": "BPME",
  "ZVQS3FLE": "STV160E",
  "ZHQSBFLE": "STHE",
  "MQSBFLE": "BPME",
  "QSBFLE": "Q826E",
  "ZVQS4FLE": "STV160E",
  "QS4FLE": "Q826E",
  "MQS4FLE": "BPME",
  "SF2FLE.1": "S334E",
  "ZHQEAE25": "STHE",
  "QEAE.25": "Q826E",
  "MQEAE25": "BPME",
  "ZVQD5E25": "STV160E",
  "QD5E.25": "Q826E",
  "MQD5E25": "BPME",
  "B2E.58": "B5907E",
  "MQF6E13": "BPME",
  "QF6E.13": "Q557E",
  "B2E.59": "B5907E",
  "MQD5E26": "BPME",
  "QD5E.26": "Q826E",
  "ZVQD5E26": "STV160E",
  "MQEAE26": "BPME",
  "QEAE.26": "Q826E",
  "ZHQEAE26": "STHE",
  "SF2FLE.2": "S334E",
  "MQF4E21": "BPME",
  "QF4E.21": "Q1015E",
  "ZHQF4E21": "STHE",
  "ZVQD3E21": "STV160E",
  "QD3E.21": "Q826E",
  "MQD3E21": "BPME",
  "SD3FLE.1": "S1030E",
  "B2E.60": "B5907E",
  "QF2E.25": "Q557E",
  "MQF2E25": "BPME",
  "ZHQF2E25": "STHE",
  "MQD1E13": "BPME",
  "QD1E.13": "Q1015E",
  "ZVQD1E13": "STV160E",
  "ZHQF2E26": "STHE",
  "MQF2E26": "BPME",
  "QF2E.26": "Q557E",
  "B2E.61": "B5907E",
  "SD3FLE.2": "S1030E",
  "MQD3E22": "BPME",
  "QD3E.22": "Q826E",
  "ZVQD3E22": "STV160E",
  "SKBFLE.1": "S344E",
  "ZHQF4E22": "STHE",
  "QF4E.22": "Q1015E",
  "MQF4E22": "BPME",
  "SF4FLE.1": "S334E",
  "ZHQEAE27": "STHE",
  "QEAE.27": "Q826E",
  "MQEAE27": "BPME",
  "ZVQD5E27": "STV160E",
  "QD5E.27": "Q826E",
  "MQD5E27": "BPME",
  "B2E.62": "B5907E",
  "MQF6E14": "BPME",
  "QF6E.14": "Q557E",
  "B2E.63": "B5907E",
  "MQD5E28": "BPME",
  "QD5E.28": "Q826E",
  "ZVQD5E28": "STV160E",
  "MQEAE28": "BPME",
  "QEAE.28": "Q826E",
  "ZHQEAE28": "STHE",
  "SF4FLE.2": "S334E",
  "MQF4E23": "BPME",
  "QF4E.23": "Q1015E",
  "ZHQF4E23": "STHE",
  "SKBFLE.2": "S344E",
  "ZVQD3E23": "STV160E",
  "QD3E.23": "Q826E",
  "MQD3E23": "BPME",
  "SD5FLE.1": "S1030E",
  "B2E.64": "B5907E",
  "QF2E.27": "Q557E",
  "MQF2E27": "BPME",
  "ZHQF2E27": "STHE",
  "MQD1E14": "BPME",
  "QD1E.14": "Q1015E",
  "ZVQD1E14": "STV160E",
  "ZHQF2E28": "STHE",
  "MQF2E28": "BPME",
  "QF2E.28": "Q557E",
  "B2E.65": "B5907E",
  "SD5FLE.2": "S1030E",
  "MQD3E24": "BPME",
  "QD3E.24": "Q826E",
  "ZVQD3E24": "STV160E",
  "SKCFLE.1": "S344E",
  "ZHQF4E24": "STHE",
  "QF4E.24": "Q1015E",
  "MQF4E24": "BPME",
  "SF6FLE.1": "S334E",
  "ZHQEAE29": "STHE",
  "QEAE.29": "Q826E",
  "MQEAE29": "BPME",
  "ZVQD5E29": "STV160E",
  "QD5E.29": "Q826E",
  "MQD5E29": "BPME",
  "B2E.66": "B5907E",
  "MQF6E15": "BPME",
  "QF6E.15": "Q557E",
  "B2E.67": "B5907E",
  "MQD5E30": "BPME",
  "QD5E.30": "Q826E",
  "ZVQD5E30": "STV160E",
  "MQEAE30": "BPME",
  "QEAE.30": "Q826E",
  "ZHQEAE30": "STHE",
  "SF6FLE.2": "S334E",
  "MQF4E25": "BPME",
  "QF4E.25": "Q1015E",
  "ZHQF4E25": "STHE",
  "SKCFLE.2": "S344E",
  "ZVQD3E25": "STV160E",
  "QD3E.25": "Q826E",
  "MQD3E25": "BPME",
  "SD7FLE.1": "S1030E",
  "B2E.68": "B5907E",
  "QF2E.29": "Q557E",
  "MQF2E29": "BPME",
  "ZHQF2E29": "STHE",
  "MQD1E15": "BPME",
  "QD1E.15": "Q1015E",
  "ZVQD1E15": "STV160E",
  "ZHQF2E30": "STHE",
  "MQF2E30": "BPME",
  "QF2E.30": "Q557E",
  "B2E.69": "B5907E",
  "SD7FLE.2": "S1030E",
  "MQT1FOE1": "BPME",
  "QT1FOE.1": "Q826E",
  "ZVQT1FOE1": "STV160E",
  "ZVQT2FOE1": "STV160E",
  "QT2FOE.1": "Q1015E",
  "MQT2FOE1": "BPME",
  "SF8FOE.1": "S334E",
  "ZHQTAFOE1": "STHE",
  "QTAFOE.1": "Q826E",
  "MQTAFOE1": "BPME",
  "ZVQT3FOE1": "STV160E",
  "QT3FOE.1": "Q826E",
  "MQT3FOE1": "BPME",
  "B2E.70": "B5907E",
  "MQT4FOE1": "BPME",
  "QT4FOE.1": "Q826E",
  "ZVQT4FOE1": "STV160E",
  "MQTBFOE1": "BPME",
  "QTBFOE.1": "Q826newE",
  "ZHQTBFOE1": "STHE",
  "MQT5FOE": "BPME",
  "QT5FOE": "Q826E",
  "ZVQT5FOE": "STV160E",
  "ZHQTBFOE2": "STHE",
  "QTBFOE.2": "Q826newE",
  "MQTBFOE2": "BPME",
  "ZVQT4FOE2": "STV160E",
  "QT4FOE.2": "Q826E",
  "MQT4FOE2": "BPME",
  "B2E.71": "B5907E",
  "MQT3FOE2": "BPME",
  "QT3FOE.2": "Q826E",
  "ZVQT3FOE2": "STV160E",
  "MQTAFOE2": "BPME",
  "QTAFOE.2": "Q826E",
  "ZHQTAFOE2": "STHE",
  "SF8FOE.2": "S334E",
  "MQT2FOE2": "BPME",
  "QT2FOE.2": "Q1015E",
  "ZVQT2FOE2": "STV160E",
  "ZVQT1FOE2": "STV160E",
  "QT1FOE.2": "Q826E",
  "MQT1FOE2": "BPME",
  "SD7ORE.1": "S1030E",
  "B2E.72": "B5907E",
  "QF2E.31": "Q557E",
  "MQF2E31": "BPME",
  "ZHQF2E31": "STHE",
  "MQD1E16": "BPME",
  "QD1E.16": "Q1015E",
  "ZVQD1E16": "STV160E",
  "ZHQF2E32": "STHE",
  "MQF2E32": "BPME",
  "QF2E.32": "Q557E",
  "B2E.73": "B5907E",
  "SD7ORE.2": "S1030E",
  "MQD3E26": "BPME",
  "QD3E.26": "Q826E",
  "ZVQD3E26": "STV160E",
  "ZHQF4E26": "STHE",
  "QF4E.26": "Q1015E",
  "MQF4E26": "BPME",
  "SF6ORE.1": "S334E",
  "ZHQEAE31": "STHE",
  "QEAE.31": "Q826E",
  "MQEAE31": "BPME",
  "ZVQD5E31": "STV160E",
  "QD5E.31": "Q826E",
  "MQD5E31": "BPME",
  "B2E.74": "B5907E",
  "MQF6E16": "BPME",
  "QF6E.16": "Q557E",
  "B2E.75": "B5907E",
  "MQD5E32": "BPME",
  "QD5E.32": "Q826E",
  "ZVQD5E32": "STV160E",
  "MQEAE32": "BPME",
  "QEAE.32": "Q826E",
  "ZHQEAE32": "STHE",
  "SF6ORE.2": "S334E",
  "MQF4E27": "BPME",
  "QF4E.27": "Q1015E",
  "ZHQF4E27": "STHE",
  "ZVQD3E27": "STV160E",
  "QD3E.27": "Q826E",
  "MQD3E27": "BPME",
  "SD5ORE.1": "S1030E",
  "B2E.76": "B5907E",
  "QF2E.33": "Q557E",
  "MQF2E33": "BPME",
  "ZHQF2E33": "STHE",
  "MQD1E17": "BPME",
  "QD1E.17": "Q1015E",
  "ZVQD1E17": "STV160E",
  "ZHQF2E34": "STHE",
  "MQF2E34": "BPME",
  "QF2E.34": "Q557E",
  "B2E.77": "B5907E",
  "SD5ORE.2": "S1030E",
  "MQD3E28": "BPME",
  "QD3E.28": "Q826E",
  "ZVQD3E28": "STV160E",
  "ZHQF4E28": "STHE",
  "QF4E.28": "Q1015E",
  "MQF4E28": "BPME",
  "SF4ORE.1": "S334E",
  "ZHQEAE33": "STHE",
  "QEAE.33": "Q826E",
  "MQEAE33": "BPME",
  "ZVQD5E33": "STV160E",
  "QD5E.33": "Q826E",
  "MQD5E33": "BPME",
  "B2E.78": "B5907E",
  "MQF6E17": "BPME",
  "QF6E.17": "Q557E",
  "B2E.79": "B5907E",
  "MQD5E34": "BPME",
  "QD5E.34": "Q826E",
  "ZVQD5E34": "STV160E",
  "MQEAE34": "BPME",
  "QEAE.34": "Q826E",
  "ZHQEAE34": "STHE",
  "SF4ORE.2": "S334E",
  "MQF4E29": "BPME",
  "QF4E.29": "Q1015E",
  "ZHQF4E29": "STHE",
  "ZVQD3E29": "STV160E",
  "QD3E.29": "Q826E",
  "MQD3E29": "BPME",
  "SD3ORE.1": "S1030E",
  "B2E.80": "B5907E",
  "QF2E.35": "Q557E",
  "MQF2E35": "BPME",
  "ZHQF2E35": "STHE",
  "MQD1E18": "BPME",
  "QD1E.18": "Q1015E",
  "ZVQD1E18": "STV160E",
  "ZHQF2E36": "STHE",
  "MQF2E36": "BPME",
  "QF2E.36": "Q557E",
  "B2E.81": "B5907E",
  "SD3ORE.2": "S1030E",
  "MQD3E30": "BPME",
  "QD3E.30": "Q826E",
  "ZVQD3E30": "STV160E",
  "ZHQF4E30": "STHE",
  "QF4E.30": "Q1015E",
  "MQF4E30": "BPME",
  "SF2ORE.1": "S334E",
  "ZHQEAE35": "STHE",
  "QEAE.35": "Q826E",
  "MQEAE35": "BPME",
  "ZVQD5E35": "STV160E",
  "QD5E.35": "Q826E",
  "MQD5E35": "BPME",
  "B2E.82": "B5907E",
  "MQF6E18": "BPME",
  "QF6E.18": "Q557E",
  "B2E.83": "B5907E",
  "MQD5E36": "BPME",
  "QD5E.36": "Q826E",
  "ZVQD5E36": "STV160E",
  "MQEAE36": "BPME",
  "QEAE.36": "Q826E",
  "ZHQEAE36": "STHE",
  "SF2ORE.2": "S334E",
  "MQS4OE1": "BPME",
  "QS4OE.1": "Q826E",
  "ZHQS4OE1": "STHE",
  "ZVQSBOE1": "STV160E",
  "QSBOE.1": "Q826E",
  "MQSBOE1": "BPME",
  "MQS3ORE": "BPME",
  "QS3ORE": "Q816E",
  "BS2ORE.1": "B2230LE",
  "BS2ORE.2": "B2230LE",
  "QS2ORE": "Q557E",
  "MQS2ORE": "BPME",
  "BSWORE": "B2900E",
  "MQR7ORE": "BPME",
  "QR7ORE": "Q826E",
  "ZVQR7ORE": "STV160E",
  "ZHQR6ORE": "STHE",
  "QR6ORE": "Q1015E",
  "MQR6ORE": "BPME",
  "ZVQR5ORE": "STV287E",
  "MQR5ORE": "BPME",
  "QR5ORE": "Q460E",
  "BW2ORE.1": "B346uE",
  "BW1ORE.1": "B346dE",
  "BW1ORE.2": "B346uE",
  "BW2ORE.2": "B346dE",
  "BW2ORE.3": "B346uE",
  "BW1ORE.3": "B346dE",
  "BW1ORE.4": "B346uE",
  "BW2ORE.4": "B346dE",
  "BW2ORE.5": "B346uE",
  "BW1ORE.5": "B346dE",
  "BW1ORE.6": "B346uE",
  "BW2ORE.6": "B346dE",
  "ZHQR4ORE": "STHE",
  "MQR4ORE": "BPME",
  "QR4ORE": "Q460E",
  "BW1ORE.7": "B346uE",
  "BW2ORE.7": "B346dE",
  "BW2ORE.8": "B346uE",
  "BW1ORE.8": "B346dE",
  "BW1ORE.9": "B346uE",
  "BW2ORE.9": "B346dE",
  "BW2ORE.10": "B346uE",
  "BW1ORE.10": "B346dE",
  "BW1ORE.11": "B346uE",
  "BW2ORE.11": "B346dE",
  "BW2ORE.12": "B346uE",
  "BW1ORE.12": "B346dE",
  "ZVQR3ORE": "STV287E",
  "MQR3ORE": "BPME",
  "QR3ORE": "Q460E",
  "BW2ORE.13": "B346uE",
  "BW1ORE.13": "B346dE",
  "BW1ORE.14": "B346uE",
  "BW2ORE.14": "B346dE",
  "BW2ORE.15": "B346uE",
  "BW1ORE.15": "B346dE",
  "BW1ORE.16": "B346uE",
  "BW2ORE.16": "B346dE",
  "BW2ORE.17": "B346uE",
  "BW1ORE.17": "B346dE",
  "BW1ORE.18": "B346uE",
  "BW2ORE.18": "B346dE",
  "ZHQR2ORE": "STHE",
  "MQR2ORE": "BPME",
  "QR2ORE": "Q460E",
  "BW1ORE.19": "B346uE",
  "BW2ORE.19": "B346dE",
  "BW2ORE.20": "B346uE",
  "BW1ORE.20": "B346dE",
  "BW1ORE.21": "B346uE",
  "BW2ORE.21": "B346dE",
  "BW2ORE.22": "B346uE",
  "BW1ORE.22": "B346dE",
  "BW1ORE.23": "B346uE",
  "BW2ORE.23": "B346dE",
  "BW2ORE.24": "B346uE",
  "BW1ORE.24": "B346dE",
  "ZVQDWOE1": "STV287E",
  "MQDWOE1": "BPME",
  "QDWOE.1": "Q460E",
  "BW2ORE.25": "B346uE",
  "BW1ORE.25": "B346dE",
  "BW1ORE.26": "B346uE",
  "BW2ORE.26": "B346dE",
  "BW2ORE.27": "B346uE",
  "BW1ORE.27": "B346dE",
  "BW1ORE.28": "B346uE",
  "BW2ORE.28": "B346dE",
  "BW2ORE.29": "B346uE",
  "BW1ORE.29": "B346dE",
  "BW1ORE.30": "B346uE",
  "BW2ORE.30": "B346dE",
  "ZHQFWOE": "STHE",
  "MQFWOE": "BPME",
  "QFWOE": "Q460E",
  "BW1ORE.31": "B346uE",
  "BW2ORE.31": "B346dE",
  "BW2ORE.32": "B346uE",
  "BW1ORE.32": "B346dE",
  "BW1ORE.33": "B346uE",
  "BW2ORE.33": "B346dE",
  "BW2ORE.34": "B346uE",
  "BW1ORE.34": "B346dE",
  "BW1ORE.35": "B346uE",
  "BW2ORE.35": "B346dE",
  "BW2ORE.36": "B346uE",
  "BW1ORE.36": "B346dE",
  "ZVQDWOE2": "STV287E",
  "MQDWOE2": "BPME",
  "QDWOE.2": "Q460E",
  "ZHQFROE2": "STHE",
  "MQFROE2": "BPME",
  "QFROE.2": "Q1080E",
  "ZVQDROE3": "STV210E",
  "MQDROE3": "BPME",
  "QDROE.3": "Q1080E",
  "ZHQFROE3": "STHE",
  "MQFROE3": "BPME",
  "QFROE.3": "Q1080E",
  "ZVQDROE4": "STV210E",
  "MQDROE4": "BPME",
  "QDROE.4": "Q1080E",
  "MQFROE4": "BPME",
  "QFROE.4": "Q1080E",
  "ZHQFROE4": "STHE",
  "MQDROE5": "BPME",
  "QDROE.5": "Q1080E",
  "ZVQDROE5": "STV210E",
  "MQFROE5": "BPME",
  "QFROE.5": "Q1080E",
  "ZHQFROE5": "STHE",
  "MQDROE6": "BPME",
  "QDROE.6": "Q1080E",
  "ZVQDROE6": "STV210E",
  "MQR2OLE": "BPME",
  "QR2OLE": "Q1080E",
  "ZHQR2OLE": "STHE",
  "MQR3OLE": "BPME",
  "QR3OLE": "Q1080E",
  "ZVQR3OLE": "STV210E",
  "MQR4OLE": "BPME",
  "QR4OLE": "Q1080E",
  "ZHQR4OLE": "STHE",
  "MQR5OLE": "BPME",
  "QR5OLE": "Q1080E",
  "ZVQR5OLE": "STV279E",
  "MQR6OLE": "BPME",
  "QR6OLE": "Q1015E",
  "ZHQR6OLE": "STHE",
  "ZVQR7OLE": "STV279E",
  "QR7OLE": "Q826E",
  "MQR7OLE": "BPME",
  "BSWOLE": "B2900RE",
  "QS2OLE": "Q557E",
  "MQS2OLE": "BPME",
  "B2E.85": "B5907E",
  "QS3OLE": "Q816E",
  "MQS3OLE": "BPME",
  "MQSBOE2": "BPME",
  "QSBOE.2": "Q826E",
  "ZVQSBOE2": "STV160E",
  "ZHQS4OE2": "STHE",
  "QS4OE.2": "Q826E",
  "MQS4OE2": "BPME",
  "SF2OLE.1": "S334E",
  "ZHQEAE37": "STHE",
  "QEAE.37": "Q826E",
  "MQEAE37": "BPME",
  "ZVQD5E37": "STV160E",
  "QD5E.37": "Q826E",
  "MQD5E37": "BPME",
  "B2E.86": "B5907E",
  "MQF6E19": "BPME",
  "QF6E.19": "Q557E",
  "B2E.87": "B5907E",
  "MQD5E38": "BPME",
  "QD5E.38": "Q826E",
  "ZVQD5E38": "STV160E",
  "MQEAE38": "BPME",
  "QEAE.38": "Q826E",
  "ZHQEAE38": "STHE",
  "SF2OLE.2": "S334E",
  "MQF4E31": "BPME",
  "QF4E.31": "Q1015E",
  "ZHQF4E31": "STHE",
  "ZVQD3E31": "STV160E",
  "QD3E.31": "Q826E",
  "MQD3E31": "BPME",
  "SD3OLE.1": "S1030E",
  "B2E.88": "B5907E",
  "QF2E.37": "Q557E",
  "MQF2E37": "BPME",
  "ZHQF2E37": "STHE",
  "MQD1E19": "BPME",
  "QD1E.19": "Q1015E",
  "ZVQD1E19": "STV160E",
  "ZHQF2E38": "STHE",
  "MQF2E38": "BPME",
  "QF2E.38": "Q557E",
  "B2E.89": "B5907E",
  "SD3OLE.2": "S1030E",
  "MQD3E32": "BPME",
  "QD3E.32": "Q826E",
  "ZVQD3E32": "STV160E",
  "ZHQF4E32": "STHE",
  "QF4E.32": "Q1015E",
  "MQF4E32": "BPME",
  "SF4OLE.1": "S334E",
  "ZHQEAE39": "STHE",
  "QEAE.39": "Q826E",
  "MQEAE39": "BPME",
  "ZVQD5E39": "STV160E",
  "QD5E.39": "Q826E",
  "MQD5E39": "BPME",
  "B2E.90": "B5907E",
  "MQF6E20": "BPME",
  "QF6E.20": "Q557E",
  "B2E.91": "B5907E",
  "MQD5E40": "BPME",
  "QD5E.40": "Q826E",
  "ZVQD5E40": "STV160E",
  "MQEAE40": "BPME",
  "QEAE.40": "Q826E",
  "ZHQEAE40": "STHE",
  "SF4OLE.2": "S334E",
  "MQF4E33": "BPME",
  "QF4E.33": "Q1015E",
  "ZHQF4E33": "STHE",
  "ZVQD3E33": "STV160E",
  "QD3E.33": "Q826E",
  "MQD3E33": "BPME",
  "SD5OLE.1": "S1030E",
  "B2E.92": "B5907E",
  "QF2E.39": "Q557E",
  "MQF2E39": "BPME",
  "ZHQF2E39": "STHE",
  "MQD1E20": "BPME",
  "QD1E.20": "Q1015E",
  "ZVQD1E20": "STV160E",
  "ZHQF2E40": "STHE",
  "MQF2E40": "BPME",
  "QF2E.40": "Q557E",
  "B2E.93": "B5907E",
  "SD5OLE.2": "S1030E",
  "MQD3E34": "BPME",
  "QD3E.34": "Q826E",
  "ZVQD3E34": "STV160E",
  "ZHQF4E34": "STHE",
  "QF4E.34": "Q1015E",
  "MQF4E34": "BPME",
  "SF6OLE.1": "S334E",
  "ZHQEAE41": "STHE",
  "QEAE.41": "Q826E",
  "MQEAE41": "BPME",
  "ZVQD5E41": "STV160E",
  "QD5E.41": "Q826E",
  "MQD5E41": "BPME",
  "B2E.94": "B5907E",
  "MQF6E21": "BPME",
  "QF6E.21": "Q557E",
  "B2E.95": "B5907E",
  "MQD5E42": "BPME",
  "QD5E.42": "Q826E",
  "ZVQD5E42": "STV160E",
  "MQEAE42": "BPME",
  "QEAE.42": "Q826E",
  "ZHQEAE42": "STHE",
  "SF6OLE.2": "S334E",
  "MQF4E35": "BPME",
  "QF4E.35": "Q1015E",
  "ZHQF4E35": "STHE",
  "ZVQD3E35": "STV160E",
  "QD3E.35": "Q826E",
  "MQD3E35": "BPME",
  "SD7OLE.1": "S1030E",
  "B2E.96": "B5907E",
  "QF2E.41": "Q557E",
  "MQF2E41": "BPME",
  "ZHQF2E41": "STHE",
  "MQD1E21": "BPME",
  "QD1E.21": "Q1015E",
  "ZVQD1E21": "STV160E",
  "ZHQF2E42": "STHE",
  "MQF2E42": "BPME",
  "QF2E.42": "Q557E",
  "B2E.97": "B5907E",
  "SD7OLE.2": "S1030E",
  "MQT1OTE1": "BPME",
  "QT1OTE.1": "Q826E",
  "ZVQT1OTE1": "STV160E",
  "ZVQT2OTE1": "STV160E",
  "QT2OTE.1": "Q1015E",
  "MQT2OTE1": "BPME",
  "SF8OTE.1": "S334E",
  "ZHQTAOTE1": "STHE",
  "QTAOTE.1": "Q826E",
  "MQTAOTE1": "BPME",
  "ZVQT3OTE1": "STV160E",
  "QT3OTE.1": "Q826E",
  "MQT3OTE1": "BPME",
  "B2E.98": "B5907E",
  "MQT4OTE1": "BPME",
  "QT4OTE.1": "Q826E",
  "ZVQT4OTE1": "STV160E",
  "MQTBOTE1": "BPME",
  "QTBOTE.1": "Q826newE",
  "ZHQTBOTE1": "STHE",
  "MQT5OTE": "BPME",
  "QT5OTE": "Q826E",
  "ZVQT5OTE": "STV160E",
  "ZHQTBOTE2": "STHE",
  "QTBOTE.2": "Q826newE",
  "MQTBOTE2": "BPME",
  "ZVQT4OTE2": "STV160E",
  "QT4OTE.2": "Q826E",
  "MQT4OTE2": "BPME",
  "B2E.99": "B5907E",
  "MQT3OTE2": "BPME",
  "QT3OTE.2": "Q826E",
  "ZVQT3OTE2": "STV160E",
  "MQTAOTE2": "BPME",
  "QTAOTE.2": "Q826E",
  "ZHQTAOTE2": "STHE",
  "SF8OTE.2": "S334E",
  "MQT2OTE2": "BPME",
  "QT2OTE.2": "Q1015E",
  "ZVQT2OTE2": "STV160E",
  "ZVQT1OTE2": "STV160E",
  "QT1OTE.2": "Q826E",
  "MQT1OTE2": "BPME",
  "SD7TRE.1": "S1030E",
  "B2E.100": "B5907E",
  "QF2E.43": "Q557E",
  "MQF2E43": "BPME",
  "ZHQF2E43": "STHE",
  "MQD1E22": "BPME",
  "QD1E.22": "Q1015E",
  "ZVQD1E22": "STV160E",
  "ZHQF2E44": "STHE",
  "MQF2E44": "BPME",
  "QF2E.44": "Q557E",
  "B2E.101": "B5907E",
  "SD7TRE.2": "S1030E",
  "MQD3E36": "BPME",
  "QD3E.36": "Q826E",
  "ZVQD3E36": "STV160E",
  "ZHQF4E36": "STHE",
  "QF4E.36": "Q1015E",
  "MQF4E36": "BPME",
  "SF6TRE.1": "S334E",
  "ZHQEAE43": "STHE",
  "QEAE.43": "Q826E",
  "MQEAE43": "BPME",
  "ZVQD5E43": "STV160E",
  "QD5E.43": "Q826E",
  "MQD5E43": "BPME",
  "B2E.102": "B5907E",
  "MQF6E22": "BPME",
  "QF6E.22": "Q557E",
  "B2E.103": "B5907E",
  "MQD5E44": "BPME",
  "QD5E.44": "Q826E",
  "ZVQD5E44": "STV160E",
  "MQEAE44": "BPME",
  "QEAE.44": "Q826E",
  "ZHQEAE44": "STHE",
  "SF6TRE.2": "S334E",
  "MQF4E37": "BPME",
  "QF4E.37": "Q1015E",
  "ZHQF4E37": "STHE",
  "ZVQD3E37": "STV160E",
  "QD3E.37": "Q826E",
  "MQD3E37": "BPME",
  "SD5TRE.1": "S1030E",
  "B2E.104": "B5907E",
  "QF2E.45": "Q557E",
  "MQF2E45": "BPME",
  "ZHQF2E45": "STHE",
  "MQD1E23": "BPME",
  "QD1E.23": "Q1015E",
  "ZVQD1E23": "STV160E",
  "ZHQF2E46": "STHE",
  "MQF2E46": "BPME",
  "QF2E.46": "Q557E",
  "B2E.105": "B5907E",
  "SD5TRE.2": "S1030E",
  "MQD3E38": "BPME",
  "QD3E.38": "Q826E",
  "ZVQD3E38": "STV160E",
  "ZHQF4E38": "STHE",
  "QF4E.38": "Q1015E",
  "MQF4E38": "BPME",
  "SF4TRE.1": "S334E",
  "ZHQEAE45": "STHE",
  "QEAE.45": "Q826E",
  "MQEAE45": "BPME",
  "ZVQD5E45": "STV160E",
  "QD5E.45": "Q826E",
  "MQD5E45": "BPME",
  "B2E.106": "B5907E",
  "MQF6E23": "BPME",
  "QF6E.23": "Q557E",
  "B2E.107": "B5907E",
  "MQD5E46": "BPME",
  "QD5E.46": "Q826E",
  "ZVQD5E46": "STV160E",
  "MQEAE46": "BPME",
  "QEAE.46": "Q826E",
  "ZHQEAE46": "STHE",
  "SF4TRE.2": "S334E",
  "MQF4E39": "BPME",
  "QF4E.39": "Q1015E",
  "ZHQF4E39": "STHE",
  "ZVQD3E39": "STV160E",
  "QD3E.39": "Q826E",
  "MQD3E39": "BPME",
  "SD3TRE.1": "S1030E",
  "B2E.108": "B5907E",
  "QF2E.47": "Q557E",
  "MQF2E47": "BPME",
  "ZHQF2E47": "STHE",
  "MQD1E24": "BPME",
  "QD1E.24": "Q1015E",
  "ZVQD1E24": "STV160E",
  "ZHQF2E48": "STHE",
  "MQF2E48": "BPME",
  "QF2E.48": "Q557E",
  "B2E.109": "B5907E",
  "SD3TRE.2": "S1030E",
  "MQD3E40": "BPME",
  "QD3E.40": "Q826E",
  "ZVQD3E40": "STV160E",
  "ZHQF4E40": "STHE",
  "QF4E.40": "Q1015E",
  "MQF4E40": "BPME",
  "QLA10RE": "Q826E",
  "MQLA10RE": "BPME",
  "ZHQLA10RE": "STHE",
  "ZVQLA9RE": "STV279E",
  "MQLA9RE": "BPME",
  "QLA9RE": "Q826E",
  "BLA6RE.1": "B5907E",
  "QLA8RE": "Q557E",
  "MQLA8RE": "BPME",
  "BLA6RE.2": "B5907E",
  "QLA7RE": "Q826E",
  "MQLA7RE": "BPME",
  "ZVQLA7RE": "STV279E",
  "QLA6RE": "Q826E",
  "MQLA6RE": "BPME",
  "ZHQLA6RE": "STHE",
  "QLA5RE": "Q826E",
  "MQLA5RE": "BPME",
  "ZVQLA5RE": "STV279E",
  "BLA4RE": "B5907E",
  "QLA4RE": "Q557E",
  "MQLA4RE": "BPME",
  "ZVF4RE": "STVFB279E",
  "QLA3RE": "Q560newE",
  "MQLA3RE": "BPME",
  "ZVQLA3RE": "STV287E",
  "BLA2RE": "B4000E",
  "ZHQLA2RE": "STHE",
  "QLA2RE": "Q560newE",
  "MQLA2RE": "BPME",
  "SLXTRE.1": "S500E",
  "QLX2RE.1": "Q560newE",
  "MQLX2RE1": "BPME",
  "ZHQLX2RE1": "STHE",
  "ZVQLX3RE1": "STV287E",
  "MQLX3RE1": "BPME",
  "QLX3RE.1": "Q560newE",
  "BLX1RE.1": "B4000RE",
  "QLX4RE": "Q560newE",
  "MQLX4RE": "BPME",
  "BLX1RE.2": "B4000RE",
  "QLX3RE.2": "Q560newE",
  "MQLX3RE2": "BPME",
  "ZVQLX3RE2": "STV287E",
  "ZHQLX2RE2": "STHE",
  "MQLX2RE2": "BPME",
  "QLX2RE.2": "Q560newE",
  "SLXTRE.2": "S500E",
  "MQLB8RE": "BPME",
  "QLB8RE": "Q560newE",
  "ZHQLB8RE": "STHE",
  "ZVF3RE": "STVFB279E",
  "QLB7RE": "Q1120newE",
  "MQLB7RE": "BPME",
  "ZVQLB7RE": "STV287E",
  "BLB2RE": "B4000E",
  "ZHQLB4RE": "STHE",
  "QLB4RE": "Q560newE",
  "MQLB4RE": "BPME",
  "ZVQLB1RE": "STV287E",
  "QLB1RE": "Q560newE",
  "MQLB1RE": "BPME",
  "SLYTRE1": "S600E",
  "QLY2RE.1": "Q460E",
  "MQLY2RE1": "BPME",
  "ZVQLY2RE1": "STV287E",
  "ZVQLY4RE1": "STV287E",
  "MQLY4RE1": "BPME",
  "QLY4RE.1": "Q560newE",
  "BLY2RE.1": "B4000E",
  "QLY5RE": "Q560newE",
  "MQLY5RE": "BPME",
  "BLY2RE.2": "B4000E",
  "QLY4RE.2": "Q560newE",
  "MQLY4RE2": "BPME",
  "ZVQLY4RE2": "STV287E",
  "ZVQLY2RE2": "STV287E",
  "MQLY2RE2": "BPME",
  "QLY2RE.2": "Q460E",
  "SLYTRE2": "S600E",
  "MQLC7RE": "BPME",
  "QLC7RE": "Q560newE",
  "BC4RE": "BC344E",
  "BC3RE": "BC344E",
  "MQLC6RE": "BPME",
  "QLC6RE": "Q560newE",
  "ZHQLC6RE": "STHE",
  "ZHF2RE": "STH2E",
  "ZVF2RE": "STVFB279E",
  "MQLC5RE": "BPME",
  "QLC5RE": "Q560newE",
  "BC2RE": "BC344E",
  "ZHF1RE": "STH2E",
  "ZVF1RE": "STVFB279E",
  "BC1RE": "BC344E",
  "MQLC3RE": "BPME",
  "QLC3RE": "Q560newE",
  "QKCRE": "QKnewE",
  "BLC2RE": "BLC2RE",
  "QKBRE": "QKnewE",
  "QLC2RE": "Q560newiE",
  "MQLC2RE": "BPME",
  "ZHQLC2RE": "STHLC2RE",
  "QKARE": "QKnewE",
  "QC2RE3495": "QC10E",
  "QC2RE3485": "QC10E",
  "QC2RE3475": "QC10E",
  "QC2RE3465": "QC10E",
  "QC2RE3455": "QC10E",
  "QC2RE3445": "QC10E",
  "QC2RE3435": "QC10E",
  "QC2RE3425": "QC10E",
  "QC2RE3415": "QC10E",
  "QC2RE3405": "QC10E",
  "QC2RE3395": "QC10E",
  "QC2RE3385": "QC10E",
  "QC2RE3375": "QC10E",
  "QC2RE3365": "QC10E",
  "QC2RE3355": "QC10E",
  "QC2RE3345": "QC10E",
  "QC2RE3335": "QC10E",
  "QC2RE3325": "QC10E",
  "QC2RE3315": "QC10E",
  "QC2RE3305": "QC10E",
  "QC2RE3295": "QC10E",
  "QC2RE3285": "QC10E",
  "QC2RE3275": "QC10E",
  "QC2RE3265": "QC10E",
  "QC2RE3255": "QC10E",
  "QC2RE3245": "QC10E",
  "QC2RE3235": "QC10E",
  "QC2RE3225": "QC10E",
  "QC2RE3215": "QC10E",
  "QC2RE3205": "QC10E",
  "QC2RE3195": "QC10E",
  "QC2RE3185": "QC10E",
  "QC2RE3175": "QC10E",
  "QC2RE3165": "QC10E",
  "QC2RE3155": "QC10E",
  "QC2RE3145": "QC10E",
  "QC2RE3135": "QC10E",
  "QC2RE3125": "QC10E",
  "QC2RE3115": "QC10E",
  "QC2RE3105": "QC10E",
  "QC2RE3095": "QC10E",
  "QC2RE3085": "QC10E",
  "QC2RE3075": "QC10E",
  "QC2RE3065": "QC10E",
  "QC2RE3055": "QC10E",
  "QC2RE3045": "QC10E",
  "QC2RE3035": "QC10E",
  "QC2RE3025": "QC10E",
  "QC2RE3015": "QC10E",
  "QC2RE3005": "QC10E",
  "QC2RE2995": "QC10E",
  "QC2RE2985": "QC10E",
  "QC2RE2975": "QC10E",
  "QC2RE2965": "QC10E",
  "QC2RE2955": "QC10E",
  "QC2RE2945": "QC10E",
  "QC2RE2935": "QC10E",
  "QC2RE2925": "QC10E",
  "QC2RE2915": "QC10E",
  "QC2RE2905": "QC10E",
  "QC2RE2895": "QC10E",
  "QC2RE2885": "QC10E",
  "QC2RE2875": "QC10E",
  "QC2RE2865": "QC10E",
  "QC2RE2855": "QC10E",
  "QC2RE2845": "QC10E",
  "QC2RE2835": "QC10E",
  "QC2RE2825": "QC10E",
  "QC2RE2815": "QC10E",
  "QC2RE2805": "QC10E",
  "QC2RE2795": "QC10E",
  "QC2RE2785": "QC10E",
  "QC2RE2775": "QC10E",
  "QC2RE2765": "QC10E",
  "QC2RE2755": "QC10E",
  "QC2RE2745": "QC10E",
  "QC2RE2735": "QC10E",
  "QC2RE2725": "QC10E",
  "QC2RE2715": "QC10E",
  "QC2RE2705": "QC10E",
  "QC2RE2695": "QC10E",
  "QC2RE2685": "QC10E",
  "QC2RE2675": "QC10E",
  "QC2RE2665": "QC10E",
  "QC2RE2655": "QC10E",
  "QC2RE2645": "QC10E",
  "QC2RE2635": "QC10E",
  "QC2RE2625": "QC10E",
  "QC2RE2615": "QC10E",
  "QC2RE2605": "QC10E",
  "QC2RE2595": "QC10E",
  "QC2RE2585": "QC10E",
  "QC2RE2575": "QC10E",
  "QC2RE2565": "QC10E",
  "QC2RE2555": "QC10E",
  "QC2RE2545": "QC10E",
  "QC2RE2535": "QC10E",
  "QC2RE2525": "QC10E",
  "QC2RE2515": "QC10E",
  "QC2RE2505": "QC10E",
  "MQC2RE": "BPME",
  "QC2RE2495": "QC10E",
  "QC2RE2485": "QC10E",
  "QC2RE2475": "QC10E",
  "QC2RE2465": "QC10E",
  "QC2RE2455": "QC10E",
  "QC2RE2445": "QC10E",
  "QC2RE2435": "QC10E",
  "QC2RE2425": "QC10E",
  "QC2RE2415": "QC10E",
  "QC2RE2405": "QC10E",
  "QC2RE2395": "QC10E",
  "QC2RE2385": "QC10E",
  "QC2RE2375": "QC10E",
  "QC2RE2365": "QC10E",
  "QC2RE2355": "QC10E",
  "QC2RE2345": "QC10E",
  "QC2RE2335": "QC10E",
  "QC2RE2325": "QC10E",
  "QC2RE2315": "QC10E",
  "QC2RE2305": "QC10E",
  "QC2RE2295": "QC10E",
  "QC2RE2285": "QC10E",
  "QC2RE2275": "QC10E",
  "QC2RE2265": "QC10E",
  "QC2RE2255": "QC10E",
  "QC2RE2245": "QC10E",
  "QC2RE2235": "QC10E",
  "QC2RE2225": "QC10E",
  "QC2RE2215": "QC10E",
  "QC2RE2205": "QC10E",
  "QC2RE2195": "QC10E",
  "QC2RE2185": "QC10E",
  "QC1RE2175": "Q10E",
  "QC1RE2165": "Q10E",
  "QC1RE2155": "Q10E",
  "QC1RE2145": "Q10E",
  "QC1RE2135": "Q10E",
  "QC1RE2125": "Q10E",
  "QC1RE2115": "Q10E",
  "QC1RE2105": "Q10E",
  "QC1RE2095": "Q10E",
  "QC1RE2085": "Q10E",
  "QC1RE2075": "Q10E",
  "QC1RE2065": "Q10E",
  "QC1RE2055": "Q10E",
  "QC1RE2045": "Q10E",
  "QC1RE2035": "Q10E",
  "QC1RE2025": "Q10E",
  "QC1RE2015": "Q10E",
  "QC1RE2005": "Q10E",
  "QC1RE1995": "Q10E",
  "QC1RE1985": "Q10E",
  "QC1RE1975": "Q10E",
  "QC1RE1965": "Q10E",
  "QC1RE1955": "Q10E",
  "QC1RE1945": "Q10E",
  "QC1RE1935": "Q10E",
  "QC1RE1925": "Q10E",
  "QC1RE1915": "Q10E",
  "QC1RE1905": "Q10E",
  "QC1RE1895": "Q10E",
  "QC1RE1885": "Q10E",
  "QC1RE1875": "Q10E",
  "QC1RE1865": "Q10E",
  "QC1RE1855": "Q10E",
  "QC1RE1845": "Q10E",
  "QC1RE1835": "Q10E",
  "QC1RE1825": "Q10E",
  "QC1RE1815": "Q10E",
  "QC1RE1805": "Q10E",
  "QC1RE1795": "Q10E",
  "QC1RE1785": "Q10E",
  "QC1RE1775": "Q10E",
  "QC1RE1765": "Q10E",
  "QC1RE1755": "Q10E",
  "QC1RE1745": "Q10E",
  "QC1RE1735": "Q10E",
  "QC1RE1725": "Q10E",
  "QC1RE1715": "Q10E",
  "QC1RE1705": "Q10E",
  "QC1RE1695": "Q10E",
  "QC1RE1685": "Q10E",
  "QC1RE1675": "Q10E",
  "QC1RE1665": "Q10E",
  "QC1RE1655": "Q10E",
  "QC1RE1645": "Q10E",
  "QC1RE1635": "Q10E",
  "QC1RE1625": "Q10E",
  "QC1RE1615": "Q10E",
  "QC1RE1605": "Q10E",
  "QC1RE1595": "Q10E",
  "QC1RE1585": "Q10E",
  "QC1RE1575": "Q10E",
  "QC1RE1565": "Q10E",
  "QC1RE1555": "Q10E",
  "QC1RE1545": "Q10E",
  "QC1RE1535": "Q10E",
  "QC1RE1525": "Q10E",
  "QC1RE1515": "Q10E",
  "QC1RE1505": "Q10E",
  "QC1RE1495": "Q10E",
  "QC1RE1485": "Q10E",
  "QC1RE1475": "Q10E",
  "QC1RE1465": "Q10E",
  "QC1RE1455": "Q10E",
  "QC1RE1445": "Q10E",
  "QC1RE1435": "Q10E",
  "QC1RE1425": "Q10E",
  "QC1RE1415": "Q10E",
  "QC1RE1405": "Q10E",
  "QC1RE1395": "Q10E",
  "QC1RE1385": "Q10E",
  "QC1RE1375": "Q10E",
  "QC1RE1365": "Q10E",
  "QC1RE1355": "Q10E",
  "QC1RE1345": "Q10E",
  "QC1RE1335": "Q10E",
  "QC1RE1325": "Q10E",
  "QC1RE1315": "Q10E",
  "QC1RE1305": "Q10E",
  "QC1RE1295": "Q10E",
  "QC1RE1285": "Q10E",
  "QC1RE1275": "Q10E",
  "QC1RE1265": "Q10E",
  "QC1RE1255": "Q10E",
  "QC1RE1245": "Q10E",
  "QC1RE1235": "Q10E",
  "QC1RE1225": "Q10E",
  "QC1RE1215": "Q10E",
  "QC1RE1205": "Q10E",
  "QC1RE1195": "Q10E",
  "QC1RE1185": "Q10E",
  "QC1RE1175": "Q10E",
  "QC1RE1165": "Q10E",
  "QC1RE1155": "Q10E",
  "QC1RE1145": "Q10E",
  "QC1RE1135": "Q10E",
  "QC1RE1125": "Q10E",
  "QC1RE1115": "Q10E",
  "QC1RE1105": "Q10E",
  "QC1RE1095": "Q10E",
  "QC1RE1085": "Q10E",
  "QC1RE1075": "Q10E",
  "QC1RE1065": "Q10E",
  "QC1RE1055": "Q10E",
  "QC1RE1045": "Q10E",
  "QC1RE1035": "Q10E",
  "QC1RE1025": "Q10E",
  "QC1RE1015": "Q10E",
  "QC1RE1005": "Q10E",
  "QC1RE995": "Q10E",
  "QC1RE985": "Q10E",
  "QC1RE975": "Q10E",
  "QC1RE965": "Q10E",
  "QC1RE955": "Q10E",
  "QC1RE945": "Q10E",
  "QC1RE935": "Q10E",
  "QC1RE925": "Q10E",
  "QC1RE915": "Q10E",
  "QC1RE905": "Q10E",
  "QC1RE895": "Q10E",
  "QC1RE885": "Q10E",
  "QC1RE875": "Q10E",
  "QC1RE865": "Q10E",
  "QC1RE855": "Q10E",
  "QC1RE845": "Q10E",
  "QC1RE835": "Q10E",
  "QC1RE825": "Q10E",
  "QC1RE815": "Q10E",
  "QC1RE805": "Q10E",
  "QC1RE795": "Q10E",
  "QC1RE785": "Q10E",
  "QC1RE775": "Q10E",
  "QC1RE765": "Q10E",
  "QC1RE755": "Q10E",
  "QC1RE745": "Q10E",
  "QC1RE735": "Q10E",
  "QC1RE725": "Q10E",
  "QC1RE715": "Q10E",
  "QC1RE705": "Q10E",
  "QC1RE695": "Q10E",
  "QC1RE685": "Q10E",
  "QC1RE675": "Q10E",
  "QC1RE665": "Q10E",
  "QC1RE655": "Q10E",
  "QC1RE645": "Q10E",
  "QC1RE635": "Q10E",
  "QC1RE625": "Q10E",
  "QC1RE615": "Q10E",
  "QC1RE605": "Q10E",
  "QC1RPE595": "Q10E",
  "QC1RPE585": "Q10E",
  "QC1RPE575": "Q10E",
  "QC1RPE565": "Q10E",
  "QC1RPE555": "Q10E",
  "QC1RPE545": "Q10E",
  "QC1RPE535": "Q10E",
  "MQC1RE": "BPME",
  "QC1RPE525": "Q10E",
  "QC1RPE515": "Q10E",
  "QC1RPE505": "Q10E",
  "QC1RPE495": "Q10E",
  "QC1RPE485": "Q10E",
  "QC1RPE475": "Q10E",
  "QC1RPE465": "Q10E",
  "QC1RPE455": "Q10E",
  "QC1RPE445": "Q10E",
  "QC1RPE435": "Q10E"
}